NNFunction/LoadANN.py
NNFunction/NNFunction.py
NNFunction/Test.py
NNFunction/__init__.py
NNFunction-0.0.2.dist-info/LICENSE
NNFunction-0.0.2.dist-info/METADATA
NNFunction-0.0.2.dist-info/WHEEL
NNFunction-0.0.2.dist-info/top_level.txt
NNFunction-0.0.2.dist-info/RECORD
