Metadata-Version: 2.1
Name: NNFunction
Version: 0.0.2
Summary: A simple package for modelling multidimensional non-linear functions using artificial neural networks
Home-page: https://github.com/mattkjames7/NNFunction
Author: Matthew Knight James
Author-email: mattkjames7@gmail.com
License: UNKNOWN
Platform: UNKNOWN
Classifier: Programming Language :: Python :: 3
Classifier: License :: OSI Approved :: GNU General Public License (GPL)
Classifier: Operating System :: POSIX
Requires-Dist: numpy
Requires-Dist: PyFileIO
Requires-Dist: matplotlib
Requires-Dist: tensorflow
Requires-Dist: scikit-learn
